<?xml version="1.0" encoding="UTF-8"?>
<Car>
	<Id>3012</Id>
	<TriggerId>1</TriggerId>
	<IsGrammarOk>1</IsGrammarOk>
	<Country>RUS</Country>
	<AvgQuality>0.97</AvgQuality>
	<License>M853AT|196</License>
	<MinQuality>0.92</MinQuality>
	<NumberOfUnknownChars>0</NumberOfUnknownChars>
	<ROI>
		<Left>202</Left>
		<Top>274</Top>
		<Right>477</Right>
		<Bottom>382</Bottom>
	</ROI>
	<TimeStamp>
		<Seconds>1583733100</Seconds>
		<USeconds>204286</USeconds>
		<Date>2020-03-09</Date>
		<Time>08:51:40.204286</Time>
	</TimeStamp>
	<Chars>
		<Char>
			<Index>0</Index>
			<Value>M</Value>
			<Quality>0.92</Quality>
		</Char>
		<Char>
			<Index>1</Index>
			<Value>8</Value>
			<Quality>0.98</Quality>
		</Char>
		<Char>
			<Index>2</Index>
			<Value>5</Value>
			<Quality>0.98</Quality>
		</Char>
		<Char>
			<Index>3</Index>
			<Value>3</Value>
			<Quality>1.00</Quality>
		</Char>
		<Char>
			<Index>4</Index>
			<Value>A</Value>
			<Quality>0.97</Quality>
		</Char>
		<Char>
			<Index>5</Index>
			<Value>T</Value>
			<Quality>1.00</Quality>
		</Char>
		<Char>
			<Index>6</Index>
			<Value>1</Value>
			<Quality>0.99</Quality>
		</Char>
		<Char>
			<Index>7</Index>
			<Value>9</Value>
			<Quality>0.98</Quality>
		</Char>
		<Char>
			<Index>8</Index>
			<Value>6</Value>
			<Quality>0.95</Quality>
		</Char>
	</Chars>
</Car>
